distributions/Binomialdistribution.py
distributions/Gaussiandistribution.py
distributions/Generaldistribution.py
distributions/__init__.py
sh_distributions-0.1.dist-info/METADATA
sh_distributions-0.1.dist-info/WHEEL
sh_distributions-0.1.dist-info/top_level.txt
sh_distributions-0.1.dist-info/RECORD
