Metadata-Version: 2.1
Name: sh-distributions
Version: 0.1
Summary: Binomial, Gaussian distributions
Home-page: UNKNOWN
Author: golden_ssoo
Author-email: paeuky44@gmail.com
License: UNKNOWN
Platform: UNKNOWN
